taskcrow/__init__.py
taskcrow/coordinate.py
taskcrow/error_reason.py
taskcrow/exception.py
taskcrow/job.py
taskcrow/processors/__init__.py
taskcrow/processors/processor_interface.py
taskcrow/processors/property_descriptor.py
taskcrow/properties.py
taskcrow/status.py
taskcrow/task.py
taskcrow/task_category.py
taskcrow/utils/__init__.py
taskcrow/utils/coordinate.py
taskcrow/utils/matcher.py
taskcrow/utils/naverplace.py
taskcrow/utils/sleep.py
taskcrow/utils/string_transformer.py
taskcrow/utils/uuid.py
taskcrow-0.1.6.dist-info/METADATA
taskcrow-0.1.6.dist-info/WHEEL
taskcrow-0.1.6.dist-info/RECORD
