Metadata-Version: 2.1
Name: taskcrow
Version: 0.1.6
Summary: 
Author: heeya8876
Author-email: heeya8876@naver.com
Requires-Python: >=3.10,<4.0
Classifier: Programming Language :: Python :: 3
Classifier: Programming Language :: Python :: 3.10
Classifier: Programming Language :: Python :: 3.11
Classifier: Programming Language :: Python :: 3.12
Requires-Dist: pymongo (>=4.6.1,<5.0.0)
